{
    "名称": "急性淋巴管炎",
    "描述": [
        "急性淋巴管炎多数是由于溶血性链球菌通过皮肤破损处或其他感染源蔓延到邻近淋巴管所引起，其主要病理变化为淋巴管壁和周围组织充血、水肿、增厚，淋巴管腔内充满细菌，凝固的淋巴液及脱落的内皮细胞。本病多见于四肢，往往有一条或数条红色的线向近侧延伸，沿行程有压痛，所属淋巴结可肿大、疼痛。严重者常伴有发热，头痛、全身不适、食欲不振及白细胞计数增多。故早诊断、早治疗是关键。  "
    ],
    "分类": [
        "疾病百科",
        "内科",
        "风湿免疫科",
        "急性淋巴管炎"
    ],
    "是否医保": "否",
    "患病比例": "0.021%",
    "易感人群": "无特定人群",
    "传染方式": "无传染性",
    "并发症": [
        "急性淋巴结炎"
    ],
    "就诊科室": [
        "内科",
        "风湿",
        "免疫科"
    ],
    "治疗方式": [
        "药物治疗",
        "康复治疗"
    ],
    "治疗周期": "14天",
    "治愈率": "治愈率89%",
    "治疗费用": "根据不同医院，收费标准不一致，市三甲医院约（1000——5000元）",
    "推荐": "凡患有疖时，应避免搔抓。",
    "原因": "多数是由于溶血性链球菌引起，可能来源于口咽炎症，足部真菌感染，皮肤损伤以及前述的各种皮肤，皮下化脓性感染，其主要病理变化为淋巴管壁和周围组织充血，水肿，增厚，淋巴管腔内充满细菌，凝固的淋巴液及脱落的内皮细胞，本病多见于四肢，往往有一条或数条红色的线向近侧延伸，沿行程有压痛，所属淋巴结可肿大，疼痛，严重者常伴有发热，头痛，全身不适，食欲不振及白细胞计数增多。多数是由于溶血性链球菌引起，可能来源于口咽炎症，足部真菌感染，皮肤损伤以及前述的各种皮肤，皮下化脓性感染，其主要病理变化为淋巴管壁和周围组织充血，水肿，增厚，淋巴管腔内充满细菌，凝固的淋巴液及脱落的内皮细胞，本病多见于四肢，往往有一条或数条红色的线向近侧延伸，沿行程有压痛，所属淋巴结可肿大，疼痛，严重者常伴有发热，头痛，全身不适，食欲不振及白细胞计数增多。",
    "预防": "积极防治原发病灶，凡患有疖时，应避免搔抓；积极治疗，若治疗不及时，可继发感染发生本病。",
    "症状": [
        "纵隔淋巴结增生",
        "发烧",
        "发热伴淋巴结肿...",
        "白细胞增多",
        "周身不适"
    ],
    "具体表现": [
        "1、四肢为好发部位，有损伤感染病源。2、淋巴管可见一条或数条“红线”向近侧延伸，有压痛，所属淋巴结肿大、疼痛。3、严重者往往有发热、头痛、全身不适，厌食，血象白细胞计数增加。"
    ],
    "检查": [
        "白细胞计数（WBC）",
        "全血细胞计数",
        "血常规",
        "马尿酸钠水解试验"
    ],
    "饮食保健": [
        "鸭肝",
        "芝麻",
        "葵花子仁",
        "核桃"
    ],
    "忌吃食物": [
        "啤酒",
        "黄酒",
        "白酒",
        "杏仁"
    ],
    "推荐食物": [
        "小麦粥",
        "杂粮粥",
        "蔬菜杂烩粥",
        "牛奶玉米汤",
        "萝卜豆腐汤",
        "绿豆南瓜汤",
        "清炒蘑菇",
        "清炒嫩黄瓜"
    ],
    "常用药品": [
        "头孢氨苄胶囊",
        "盐酸左氧氟沙星胶囊"
    ],
    "药品明细": [
        "普洛康裕头孢氨苄胶囊(头孢氨苄胶囊)",
        "珠海联邦盐酸左氧氟沙星胶囊(盐酸左氧氟沙星胶囊)",
        "宜昌长江乳酸左氧氟沙星片(乳酸左氧氟沙星片)",
        "可乐必妥(左氧氟沙星片)",
        "大冢制药盐酸左氧氟沙星胶囊(盐酸左氧氟沙星胶囊)",
        "康尼(盐酸米诺环素胶囊)",
        "黄河药业盐酸左氧氟沙星胶囊(盐酸左氧氟沙星胶囊)",
        "广东三才头孢氨苄胶囊(头孢氨苄胶囊)",
        "玫满(盐酸米诺环素胶囊)",
        "日中天头孢地尼分散片(头孢地尼分散片)",
        "东康药业头孢氨苄胶囊(头孢氨苄胶囊)",
        "恒健制药头孢氨苄胶囊(头孢氨苄胶囊)",
        "福邦药业盐酸左氧氟沙星胶囊(盐酸左氧氟沙星胶囊)",
        "石药欧意盐酸左氧氟沙星胶囊(盐酸左氧氟沙星胶囊)",
        "海口奇力盐酸左氧氟沙星胶囊(盐酸左氧氟沙星胶囊)",
        "宜昌人福头孢氨苄胶囊(头孢氨苄胶囊)",
        "俞氏乳酸左氧氟沙星片(乳酸左氧氟沙星片)",
        "亚邦强生药业头孢氨苄胶囊(头孢氨苄胶囊)",
        "爱普森药业盐酸左氧氟沙星胶(盐酸左氧氟沙星胶囊)",
        "兰陵制药盐酸左氧氟沙星胶囊(盐酸左氧氟沙星胶囊)",
        "洛普星(盐酸左氧氟沙星胶囊)",
        "河北天成药业乳酸左氧氟沙星(乳酸左氧氟沙星片)",
        "津兰药业头孢地尼分散片(头孢地尼分散片)"
    ]
}