{
    "名称": "颈椎后脱位",
    "描述": [
        "颈椎后脱位是指暴力使颈椎产生过伸活动引起颈椎上节椎体下缘在下节椎体上缘向后滑动而出现相应临床症状的疾病，在临床上，典型的颈椎后脱位十分少见。颈椎后脱位为严重过伸性损伤的类型之一，属完全性损伤，多伴有脊髓受损及软组织的广泛性损伤，故预后欠佳。  "
    ],
    "分类": [
        "疾病百科",
        "外科",
        "骨外科",
        "颈椎后脱位"
    ],
    "是否医保": " 否 ",
    "患病比例": "0.025%",
    "易感人群": "无特定人群  ",
    "传染方式": "无传染性",
    "并发症": [
        "瘫痪"
    ],
    "就诊科室": [
        "外科",
        "骨",
        "外科"
    ],
    "治疗方式": "支持性治疗 康复治疗",
    "治疗周期": "1-3个月",
    "治愈率": "75% ",
    "治疗费用": "根据不同医院，收费标准不一致，市三甲医院约（5000——10000元）",
    "推荐": "注意安全，避免外伤。",
    "原因": "暴力损伤（35%）：作用于面，额及颏部的暴力，如引起头颈部过度仰伸且其强度超过前纵韧带的张应力时，则该韧带首先断裂，随着暴力的持续，可引起椎间隙破裂，后方小关节仰伸，关节囊撕裂，以致因上节椎体下缘在下节椎体上缘向后滑动而出现典型的颈椎后脱位，由于其局部的各种组织中以脊髓最为娇嫩，因此，当脊髓被嵌压于上节椎体后缘及硬膜囊前壁与下节椎板前缘及黄韧带之间时，甚易引起程度不同的损伤，一般表现为脊髓中央管症候群，也可有脊髓前中央动脉症候群等。先天椎管狭窄（27%）：如该患者原本存在椎管狭窄，则可加重损伤而引起脊髓横断性改变，以致出现脊髓完全性损伤，在这种情况下多伴有局部韧带及椎间盘等软组织的严重损伤，因此稳定性差，伤后易自动复位。过伸性损伤（25%）：多为过伸性损伤造成本病的发生。作用于面，额及颏部的暴力，如引起头颈部过度仰伸且其强度超过前纵韧带的张应力时，则该韧带首先断裂，随着暴力的持续，可引起椎间隙破裂，后方小关节仰伸，关节囊撕裂，以致因上节椎体下缘在下节椎体上缘向后滑动而出现典型的颈椎后脱位，由于其局部的各种组织中以脊髓最为娇嫩，因此，当脊髓被嵌压于上节椎体后缘及硬膜囊前壁与下节椎板前缘及黄韧带之间时，甚易引起程度不同的损伤，一般表现为脊髓中央管症候群，也可有脊髓前中央动脉症候群等。如该患者原本存在椎管狭窄，则可加重损伤而引起脊髓横断性改变，以致出现脊髓完全性损伤，在这种情况下多伴有局部韧带及椎间盘等软组织的严重损伤，因此稳定性差，伤后易自动复位。多为过伸性损伤造成本病的发生。",
    "预防": "本病为外伤性疾病，无预防措施，注意安全，避免外伤。",
    "症状": [
        "颈肩痛",
        "颈部酸痛",
        "颈椎椎节已有明...",
        "皮下血肿",
        "头颈部活动受限",
        "感觉分离",
        "四肢瘫痪"
    ],
    "具体表现": [
        "多系过伸性损伤，如额面部暴力撞击史等。老年人多见。常见损伤部位集中在颈4～6节段。面部、额部可有皮肤擦伤、挫伤及皮下血肿等。颈部疼痛，颈部运动障碍，颈部肌肉痉挛。约80%以上的病例伴有脊髓中央管症候群或脊髓前中央动脉受压症候群等临床症状，前者表现为上肢重于下肢的四肢瘫痪，感觉分离及反射异常;而后者则表现为四肢痉挛性瘫痪等。"
    ],
    "检查": [
        "钼靶X线检查",
        "核磁共振成像(MRI)",
        "CT检查"
    ],
    "饮食保健": [
        "鸭肝",
        "葵花子仁",
        "白果（干）",
        "黑豆"
    ],
    "忌吃食物": [
        "白酒",
        "鹅肉",
        "油豆腐",
        "白扁豆"
    ],
    "推荐食物": [
        "小麦粥",
        "荞麦粥",
        "杂粮粥",
        "蔬菜杂烩粥",
        "羊腩萝卜丝粥",
        "豆薯小米粥",
        "花生杏仁粥",
        "瓜粒杂锦汤"
    ],
    "常用药品": [
        "骨刺片",
        "氨糖美辛肠溶片"
    ],
    "药品明细": [
        "白山长白山制药骨刺片(骨刺片)",
        "海力生氨糖美辛肠溶片(氨糖美辛肠溶片)",
        "药都樟树抗骨质增生丸(抗骨质增生丸)",
        "闽海药业抗骨增生片(抗骨增生片)",
        "西峰制药藤黄健骨胶囊(藤黄健骨胶囊)",
        "中医研究院骨筋丸胶囊(骨筋丸胶囊)",
        "康奇力药业腰息痛胶囊(腰息痛胶囊)",
        "新赣江药业腰息痛胶囊(腰息痛胶囊)",
        "茂祥制药藤黄健骨丸(藤黄健骨丸)",
        "振霖药业腰息痛胶囊(腰息痛胶囊)",
        "方兴制药骨刺平片(骨刺平片)",
        "康惠制药骨刺胶囊(骨刺胶囊)",
        "吉尔吉药业颈康胶囊(颈康胶囊)",
        "白云制药灵仙跌打片(灵仙跌打片)",
        "辅仁堂抗骨增生片(抗骨增生片)",
        "甘南藏药抗骨质增生丸(抗骨质增生丸)",
        "陕西健民骨刺平片(骨刺平片)",
        "双鼎制药抑眩宁胶囊(抑眩宁胶囊)",
        "欧莱(复方七叶皂苷钠凝胶)",
        "海天制药骨筋丸胶囊(骨筋丸胶囊)",
        "海口市制药根痛平片(根痛平片)",
        "汉典制药根痛平颗粒(根痛平颗粒)",
        "福瑞达制药颈痛片(颈痛片)"
    ]
}