{
    "名称": "吡唑酮类中毒",
    "描述": [
        "吡唑酮类药物是安替比林的衍生物，毒性较大，治疗剂量即可引起严重粒细胞减少。这类药物包括氨基比林、安乃近、保太松、羟基保太松等。氨基比林已被淘汰，临床上仅用其与其他药配合成的复方制剂，如索米痛片(去痛片)、脑宁片、安痛定片等。  "
    ],
    "分类": [
        "急诊科"
    ],
    "是否医保": "否",
    "患病比例": "0.012%",
    "易感人群": "无特发人群",
    "传染方式": "无传染性",
    "并发症": [
        "恶心和呕吐",
        "腹泻",
        "十二指肠溃疡",
        "再生障碍性贫血",
        "肝炎",
        "肺水肿",
        "高血压"
    ],
    "就诊科室": [
        "急诊科"
    ],
    "治疗方式": [
        "药物治疗",
        "支持性治疗"
    ],
    "治疗周期": "3个月",
    "治愈率": "65%",
    "治疗费用": "根据不同医院，收费标准不一致，市三甲医院约（5000-10000元）",
    "推荐": "服用本类药物应遵医嘱适量，易发生过敏反应，过敏体质人群禁用。",
    "原因": "因误服过量或长期应用较大剂量所致。少数病人虽用治疗量，亦可发生严重的中毒反应。缺氧一些毒物可引起机体的缺氧，进一步使机体器官的机能代谢发生障碍，出现中毒现象。毒物引起缺氧的原因为：(1)毒物了呼吸机能：如抑制或麻痹了呼吸中枢，或由于毒物引起喉头水肿，支氧管痉挛，呼吸肌痉挛及肺水肿等。(2)毒物引起血淮成分的改变：如发生碳氧血红蛋白，变性血红蛋白血症以及溶血等。(3)毒物使机体组织的抑制。(4)毒物引起心血管机能的破坏：如毒物对毛细血管及心肌的影响及毒物所致的休克等。因误服过量或长期应用较大剂量所致。少数病人虽用治疗量，亦可发生严重的中毒反应。缺氧一些毒物可引起机体的缺氧，进一步使机体器官的机能代谢发生障碍，出现中毒现象。毒物引起缺氧的原因为：(1)毒物了呼吸机能：如抑制或麻痹了呼吸中枢，或由于毒物引起喉头水肿，支氧管痉挛，呼吸肌痉挛及肺水肿等。(2)毒物引起血淮成分的改变：如发生碳氧血红蛋白，变性血红蛋白血症以及溶血等。(3)毒物使机体组织的抑制。(4)毒物引起心血管机能的破坏：如毒物对毛细血管及心肌的影响及毒物所致的休克等。",
    "预防": "日常预防因误服过量或长期应用较大剂量所致。少数病人虽用治疗量，亦可发生严重的中毒反应。药物中毒的诊断 对病史的询问和临床检验与一般疾病基本相同，但对药物中毒的鉴别诊断比较复杂。首先应区分病人出现毒性症状是由于病情发展所致，还是因用药引起，如头痛、头晕、恶心、呕吐等。遇有皮疹突然发生，应考虑与药物或毒物有关。医生要特别询问服药史，用药品种、剂量和时间，还要熟悉每一种药物的不良反应，了解患者家族药物毒性反应史。",
    "症状": [
        "发绀",
        "恶心",
        "心力衰竭",
        "盗汗",
        "昏迷",
        "虚脱",
        "惊厥",
        "休克",
        "水肿",
        "血尿"
    ],
    "具体表现": [
        "可出现恶心，呕吐，盗汗，皮疹，粒性细胞减少，血小板减少，胃肠道出血，血尿，凝血酶原时间延长，肝，肾功能损害，发绀，谵妄，惊厥，休克，昏迷等，或有溶血性贫血，再生障碍性贫血，发热等，安替比林较常引起高铁血红蛋白血症，小婴儿可因体温过低，虚脱或严重紫绀而致死，保太松还有水，钠，氯潴留作用，导致浮肿，血压升高，甚至发生心力衰竭和肺水肿，曾有因用治疗剂量复方氨基比林注射液发生过敏性休克。"
    ],
    "检查": [
        "肾功能检查",
        "尿常规",
        "血常规"
    ],
    "饮食保健": [
        "鹿肉",
        "鸡蛋清",
        "鸡蛋",
        "南瓜子仁"
    ],
    "忌吃食物": [
        "白酒",
        "鸡肝",
        "杏仁",
        "白扁豆"
    ],
    "推荐食物": [
        "蔬菜杂烩粥",
        "杂粮粥",
        "荞麦粥",
        "小麦粥",
        "红豆糯米粥",
        "荸荠粥",
        "花生杏仁粥",
        "冬瓜粒杂锦汤"
    ],
    "常用药品": [
        "布美他尼片",
        "十一味金色丸"
    ],
    "药品明细": [
        "桂林南药布美他尼片(布美他尼片)",
        "雄巴拉曲神水十一味金色丸(十一味金色丸)",
        "西藏甘露仁青芒觉(仁青芒觉)",
        "金诃藏药大月晶丸(大月晶丸)",
        "金诃藏药仁青芒觉(仁青芒觉)",
        "苏肽生(注射用鼠神经生长因子)",
        "新峰药业盐酸利多卡因注射液(盐酸利多卡因注射液)",
        "海斯制药盐酸利多卡因注射液(盐酸利多卡因注射液)",
        "西藏甘露十一味金色丸(十一味金色丸)",
        "卓峰地塞米松磷酸钠注射液(地塞米松磷酸钠注射液)",
        "白云山天心地塞米松磷酸钠注(地塞米松磷酸钠注射液)",
        "涟水制药地塞米松磷酸钠注射(地塞米松磷酸钠注射液)",
        "金耀药业地塞米松磷酸钠注射(地塞米松磷酸钠注射液)",
        "遂成药业地塞米松磷酸钠注射(地塞米松磷酸钠注射液)",
        "恩经复(注射用鼠神经生长因子)",
        "金路捷(注射用鼠神经生长因子)",
        "新亚注射用硫代硫酸钠(注射用硫代硫酸钠)",
        "北京永康药业盐酸利多卡因注(盐酸利多卡因注射液)",
        "北京益民药业盐酸利多卡因注(盐酸利多卡因注射液)",
        "中国大冢盐酸利多卡因注射液(盐酸利多卡因注射液)",
        "盐酸利多卡因注射液(盐酸利多卡因注射液)",
        "全星制药注射用布美他尼(注射用布美他尼)",
        "皇隆制药注射用呋塞米(注射用呋塞米)"
    ]
}