{
    "名称": "腹卒中综合征",
    "描述": [
        "腹卒中综合征（Abdominal Apoplexy Syndrome）是指腹腔内血管自发性破裂引起急腹症和休克症候群，又称之为自发性大量腹腔内出血、腹腔内卒中综合征、肠系膜或腹膜下出血综合征，病因尚不明确。有可能与原发性高血压、动脉硬化、腹腔血管发育异常以及妊娠有关系。  "
    ],
    "分类": [
        "疾病百科",
        "外科",
        "普外科",
        "腹卒中综合征"
    ],
    "是否医保": " 否 ",
    "患病比例": "发病率约为0.001%-0.002%",
    "易感人群": "多见于男性  ",
    "传染方式": "无传染性",
    "并发症": [
        "动脉硬化",
        "高血压",
        "休克"
    ],
    "就诊科室": [
        "外科",
        "普外科"
    ],
    "治疗方式": "手术治疗 药物治疗 支持治疗",
    "治疗周期": "8-12周",
    "治愈率": "75% ",
    "治疗费用": "根据不同医院，收费标准不一致，市三甲医院约（5000——20000元）",
    "推荐": "饮食方面要做到规律、合理，即以高蛋白、高维生素食物为主。",
    "原因": "腹部卒中不是一种独立性疾病，而是一组在临床上以腹腔内出血为表现的综合征，这种病例的发现往往依赖于剖腹手术，病因尚不清楚，目前研究发现，原发性高血压，门静脉高压，以及动脉粥样硬化是该病的重要危险因素，腹腔血管发育异常或先天性缺陷，妊娠与内分泌及炎症均可能与此类病例有关。一般认为，高血压动脉粥样硬化的患者，受外界或内在因素影响时，血压骤然升高，内脏动脉瘤或动脉粥样硬化薄弱区承受的压力增加，当达到一定程度时，血管可破裂出血。腹部卒中不是一种独立性疾病，而是一组在临床上以腹腔内出血为表现的综合征，这种病例的发现往往依赖于剖腹手术，病因尚不清楚，目前研究发现，原发性高血压，门静脉高压，以及动脉粥样硬化是该病的重要危险因素，腹腔血管发育异常或先天性缺陷，妊娠与内分泌及炎症均可能与此类病例有关。一般认为，高血压动脉粥样硬化的患者，受外界或内在因素影响时，血压骤然升高，内脏动脉瘤或动脉粥样硬化薄弱区承受的压力增加，当达到一定程度时，血管可破裂出血。",
    "预防": "在动脉粥样硬化的病人当中大量应用抗凝药物，虽尚无相关的大规模临床试验证实两者的相关性，但仍应警惕腹腔卒中发生的可能，在接诊病人中如出现不明原因的腹痛伴血色素进行性下降时，需高度重视。",
    "症状": [
        "血压下降",
        "面色苍白",
        "休克",
        "腹痛"
    ],
    "具体表现": [
        "1、主要为突然发生的剧裂腹痛、面色苍白、血压下降，出现休克及腹膜刺激征。2、常有躁动不安。3、深呼吸、咳嗽，转动身体时都可加剧疼痛。故病人不能变动体位。4、有些病人有腹膜刺激征，休克发生快，伴有恶心呕吐。5、突然腹痛开始时体温可以正常，之后逐渐升高。老年衰弱的病人，体温不一定随病情加重而升高。脉搏通常随体温的升高而加快。"
    ],
    "检查": [
        "腹腔穿刺",
        "腹部平片",
        "腹部外形检查",
        "血常规",
        "腹部CT"
    ],
    "饮食保健": [],
    "忌吃食物": [],
    "推荐食物": [],
    "常用药品": [
        "曲匹布通片",
        "注射用硫酸核糖霉素"
    ],
    "药品明细": [
        "湘江曲匹布通片(曲匹布通片)",
        "浙江瑞新曲匹布通片(曲匹布通片)",
        "山东仁和堂曲匹布通片(曲匹布通片)",
        "江苏四环生物曲匹布通片(曲匹布通片)",
        "山西普德注射用硫酸核糖霉素(注射用硫酸核糖霉素)",
        "上海信谊盐酸多西环素胶丸(盐酸多西环素胶丸)",
        "山东鲁抗注射用头孢哌酮钠(注射用头孢哌酮钠)",
        "先锋必注射用头孢哌酮钠(注射用头孢哌酮钠)",
        "浙江安贝特曲匹布通片(曲匹布通片)",
        "灵宝豫西曲匹布通片(曲匹布通片)",
        "仙毕注射用头孢哌酮钠(注射用头孢哌酮钠)",
        "河南润弘硫酸奈替米星注射液(硫酸奈替米星注射液)",
        "国瑞药业注射用头孢哌酮钠(注射用头孢哌酮钠)",
        "浙江震元硫酸西索米星注射液(硫酸西索米星注射液)",
        "遂成药业硫酸奈替米星注射液(硫酸奈替米星注射液)",
        "苏州中化注射用头孢哌酮钠(注射用头孢哌酮钠)",
        "浙江金华康恩贝注射用硫酸核(注射用硫酸核糖霉素)",
        "海南通用同盟硫酸奈替米星注(硫酸奈替米星注射液)",
        "辽宁澎健曲匹布通片(曲匹布通片)",
        "山西远景康业曲匹布通片(曲匹布通片)",
        "山西仟源曲匹布通片(曲匹布通片)",
        "山西普德硫酸西索米星注射液(硫酸西索米星注射液)",
        "河南鼎复康曲匹布通片(曲匹布通片)"
    ]
}