{
    "名称": "经行发热",
    "描述": [
        "每值经期或经行前后出现以发热为主的病症，称“经行发热”，又称“经来发热”。本病与西医学的慢性盆腔炎、生殖器结核、子宫内膜异位症及临床症状不明显的感染有关。经行发热，病证名。见《医宗金鉴·妇科心法要诀》：亦名经来发热，包括经行潮热。指在每次月经来潮期间，或月经前后，出现发热症状者。多因经期感受外邪、阴虚生热、血虚挟滞或血热外泛等所致。  "
    ],
    "分类": [
        "中医科",
        "中医综合"
    ],
    "是否医保": "否",
    "患病比例": "0.1%",
    "易感人群": "经期女性",
    "传染方式": "无传染性",
    "并发症": [
        "腹胀"
    ],
    "就诊科室": [
        "中医科",
        "中医",
        "综合"
    ],
    "治疗方式": [
        "药物治疗",
        "支持性治疗"
    ],
    "治疗周期": "2-4周",
    "治愈率": "90%",
    "治疗费用": "根据不同医院，收费标准不一致，市三甲医院约（500——1000元）",
    "推荐": "加强营养，少食多餐。",
    "原因": "瘀热（30%）：原有子宫内膜异位症或慢性盆腔炎病史，宿瘀滞留胞中，积瘀化热，经行之际，血海充盈，瘀热郁结，气血营卫失调而致经行发热。血热（25%）：阳盛体质，又嗜食辛热谷物，或肝郁化火，经行时冲脉之气旺盛，气火相迫，经行发热。血热多由邪热入血所致，也可由于情志郁结，五志过极化火而导致血热。　　气虚（20%）：禀赋气弱，经行时气随血耗，营卫失调而致发热。　　原有子宫内膜异位症或慢性盆腔炎病史，宿瘀滞留胞中，积瘀化热，经行之际，血海充盈，瘀热郁结，气血营卫失调而致经行发热。阳盛体质，又嗜食辛热谷物，或肝郁化火，经行时冲脉之气旺盛，气火相迫，经行发热。血热多由邪热入血所致，也可由于情志郁结，五志过极化火而导致血热。　　禀赋气弱，经行时气随血耗，营卫失调而致发热。　　",
    "预防": "经行发热由气虚或阴虚引起的，总由患者体质虚弱，经行脏腑气血或阴虚生内热所致，故经后应继续调养，并适当参加户外活动，增强体质，促进机体对经行期气血变化的适应性，可以防止经行发热。",
    "症状": [
        "腹痛",
        "子宫内膜异位",
        "月经不调"
    ],
    "具体表现": [
        "阴虚型：经期或经后午后发热，五心烦热，咽干口燥，两颧潮红，经量少，色鲜红，舌红，苔少，脉细数。肝郁型：经前或经期发热，头晕目眩，口苦咽干，烦躁易怒，乳房、胸胁、少腹胀痛，经量或多或少，经色深红，舌红，苔微腻，脉弦数。血瘀型：经前或经期发热，乍寒乍热，小腹疼痛拒按，经色紫黯，夹有血块，舌紫黯或舌边有瘀点，脉沉弦或沉涩有力。"
    ],
    "检查": [
        "ECT检查",
        "血常规",
        ""
    ],
    "饮食保健": [
        "鸭蛋",
        "鸡蛋",
        "鸡肉",
        "腰果"
    ],
    "忌吃食物": [
        "白酒",
        "杏仁",
        "腐竹",
        "田螺"
    ],
    "推荐食物": [
        "扁豆香薷汤",
        "当归生姜羊肉汤",
        "红糖生姜汁"
    ],
    "常用药品": [
        "盐酸左氧氟沙星胶囊",
        "妇乐颗粒"
    ],
    "药品明细": [
        "联邦左福康盐酸左氧氟沙星胶(盐酸左氧氟沙星胶囊)",
        "江苏康缘妇乐颗粒(妇乐颗粒)",
        "佳乐弗乳酸左氧氟沙星片(乳酸左氧氟沙星片)",
        "白马妇炎康复胶囊(妇炎康复胶囊)",
        "潘高寿丹鳖胶囊(丹鳖胶囊)",
        "湖北午时宫炎康颗粒(宫炎康颗粒)",
        "安徽新世纪盐酸左氧氟沙星胶(盐酸左氧氟沙星胶囊)",
        "花城龙胆泻肝丸(龙胆泻肝丸)",
        "博美欣(阿莫西林克拉维酸钾(4:1)分散片)",
        "今媛安止痛化癥片(止痛化癥片)",
        "北京勃然妇科分清丸(妇科分清丸)",
        "万适宁(匹多莫德片)",
        "内蒙古天奇龙胆泻肝丸(龙胆泻肝丸)",
        "可乐必妥(左氧氟沙星片)",
        "安徽济人宫炎康颗粒(宫炎康颗粒)",
        "长春普华宫炎康颗粒(宫炎康颗粒)",
        "四川大冢盐酸左氧氟沙星胶囊(盐酸左氧氟沙星胶囊)",
        "江西药都樟树白带丸(白带丸)",
        "小医神金刚藤口服液(金刚藤口服液)",
        "承德天原龙胆泻肝丸(龙胆泻肝丸)",
        "山东鲁抗诺氟沙星片(诺氟沙星片)",
        "英雄龙胆泻肝丸(龙胆泻肝丸)",
        "罗浮山宫炎平滴丸(宫炎平滴丸)"
    ]
}