{
    "名称": "脑动脉盗血综合征",
    "描述": [
        "脑动脉盗血综合征(steal syndrome)是在各种原因引起的主动脉弓及其附近大动脉血管严重狭窄和闭塞情况下，狭窄的远端脑动脉内压力明显下降，因虹吸作用使邻近的其他脑动脉血流逆流供应压力较低的动脉以代偿其供血。被盗血的脑动脉供血显著减少，相应脑组织缺血出现临床症状体征，称为脑动脉逆流综合征。包括锁骨下动脉盗血综合征、颈动脉盗血综合征、椎-基底动脉盗血综合征。缺血症状严重者可考虑手术治疗，如血管内膜剥离、血管内支架或血管重建术等。不宜使用扩血管和降血压药物。  "
    ],
    "分类": [
        "疾病百科",
        "内科",
        "神经内科",
        "脑动脉盗血综合征"
    ],
    "是否医保": "否",
    "患病比例": "0.001%",
    "易感人群": "无特发人群。",
    "传染方式": "无传染性",
    "并发症": [
        "眩晕",
        "恶心和呕吐",
        "耳鸣",
        "共济失调"
    ],
    "就诊科室": [
        "内科",
        "神经内科"
    ],
    "治疗方式": [
        "手术治疗",
        "药物治疗",
        "支持性治疗"
    ],
    "治疗周期": "10-30天",
    "治愈率": "60%",
    "治疗费用": "根据不同医院，收费标准不一致，市三甲医院约（20000——50000元）",
    "推荐": "早发现、早诊断、早治疗。",
    "原因": "动脉粥样硬化是最常见的闭塞性病因，极少数属于先天性，罕见于胸部外伤，无脉症，巨细胞动脉炎，栓塞或瘤栓。动脉粥样硬化是最常见的闭塞性病因，极少数属于先天性，罕见于胸部外伤，无脉症，巨细胞动脉炎，栓塞或瘤栓。",
    "预防": "早发现、早诊断、早治疗是关键。",
    "症状": [
        "眩晕",
        "恶心",
        "晕厥",
        "皮肤苍白",
        "轻瘫",
        "耳鸣",
        "跌倒发作",
        "共济失调"
    ],
    "具体表现": [
        "症状：眩晕、恶心、呕吐、耳鸣、肢体轻瘫、共济失调等，可有晕厥发作或跌倒发作。患肢无力、皮肤苍白、发凉、消瘦、麻木等。"
    ],
    "检查": [
        "颅脑CT检查",
        "血管造影"
    ],
    "饮食保健": [],
    "忌吃食物": [],
    "推荐食物": [],
    "常用药品": [
        "右旋糖酐20葡萄糖注射液",
        "磷酸川芎嗪氯化钠注射液"
    ],
    "药品明细": [
        "昆明宇斯右旋糖酐20葡萄糖(右旋糖酐20葡萄糖注射液)",
        "上海长征富民右旋糖酐20葡(右旋糖酐20葡萄糖注射液)",
        "青州尧王磷酸川芎嗪氯化钠注(磷酸川芎嗪氯化钠注射液)",
        "石药银湖磷酸川芎嗪氯化钠注(磷酸川芎嗪氯化钠注射液)",
        "锦州九泰磷酸川芎嗪氯化钠注(磷酸川芎嗪氯化钠注射液)",
        "天方药业右旋糖酐20葡萄糖(右旋糖酐20葡萄糖注射液)",
        "河南医科大学制药右旋糖酐2(右旋糖酐20葡萄糖注射液)",
        "内蒙古白医右旋糖酐20葡萄(右旋糖酐20葡萄糖注射液)",
        "杰力平(磷酸川芎嗪氯化钠注射液)",
        "河南天方华中右旋糖酐20葡(右旋糖酐20葡萄糖注射液)",
        "山西诺成右旋糖酐20葡萄糖(右旋糖酐20葡萄糖注射液)",
        "石药银湖右旋糖酐20葡萄糖(右旋糖酐20葡萄糖注射液)",
        "安徽丰原右旋糖酐20葡萄糖(右旋糖酐20葡萄糖注射液)",
        "大连德泽磷酸川芎嗪氯化钠注(磷酸川芎嗪氯化钠注射液)",
        "辽宁味邦右旋糖酐20葡萄糖(右旋糖酐20葡萄糖注射液)",
        "山东康宁右旋糖酐20葡萄糖(右旋糖酐20葡萄糖注射液)",
        "上海华源长富右旋糖酐20葡(右旋糖酐20葡萄糖注射液)",
        "滨雨(磷酸川芎嗪氯化钠注射液)",
        "大同星宇星火右旋糖酐20葡(右旋糖酐20葡萄糖注射液)",
        "长富维秦(磷酸川芎嗪氯化钠注射液)",
        "江苏正大丰海右旋糖酐20葡(右旋糖酐20葡萄糖注射液)",
        "河北甘泉右旋糖酐20葡萄糖(右旋糖酐20葡萄糖注射液)",
        "天津华津右旋糖酐20葡萄糖(右旋糖酐20葡萄糖注射液)"
    ]
}