{
    "url": "http://jib.xywy.com/il_sii/gaishu/4271.htm",
    "basic_info": {
        "category": [
            "疾病百科",
            "肿瘤科",
            "肿瘤内科",
            "婴儿成神经细胞瘤"
        ],
        "name": "婴儿成神经细胞瘤",
        "desc": [
            "婴儿成神经细胞瘤(infantile neuroblastoma)为幼儿最常见的恶性肿瘤，皮损发生于患本病婴儿的32%。  "
        ],
        "attributes": [
            "医保疾病： 否 ",
            "患病比例：0.0001%",
            "易感人群：见于幼儿  ",
            "传染方式：无传染性",
            "并发症：结节性红斑",
            "就诊科室：肿瘤科  肿瘤内科",
            "治疗方式：手术治疗 药物治疗 支持性治疗",
            "治疗周期：1-3个月",
            "治愈率：10% ",
            "治疗费用：根据不同医院，收费标准不一致，市三甲医院约（3000——5000元）",
            "早发现，早诊断，早治疗。"
        ]
    },
    "cause_info": "(一)发病原因病因尚不明。(二)发病机制发病机制还不清楚。(一)发病原因病因尚不明。(二)发病机制发病机制还不清楚。",
    "prevent_info": "婴儿成神经细胞瘤日常预防注意孩子平时的饮食，营养问题。",
    "symptom_info": [
        [
            "无法引出moro反应",
            "红晕",
            "眶周瘀斑",
            "虹膜异色",
            "结节",
            "我要提问"
        ],
        [
            "皮损呈多发性2～20mm大小坚实性蓝色结节，摩擦时变苍白，周围形成红晕，苍白持续1～2h，另外可见眶周瘀斑(所谓浣熊眼)和虹膜异色。"
        ]
    ],
    "inspect_info": [
        "免疫病理检查",
        "尿常规",
        "血常规"
    ],
    "treat_info": {
        "就诊科室": "肿瘤科  肿瘤内科",
        "治疗方式": "手术治疗 药物治疗 支持性治疗",
        "治疗周期": "1-3个月",
        "治愈率": "10%",
        "治疗费用": "根据不同医院，收费标准不一致，市三甲医院约（3000——5000元）"
    },
    "food_info": {
        "good": [],
        "bad": [],
        "recommand": []
    },
    "drug_info": []
}