{
    "url": "http://jib.xywy.com/il_sii/gaishu/6492.htm",
    "basic_info": {
        "category": [
            "疾病百科",
            "外科",
            "泌尿外科",
            "泌尿生殖系滴虫病"
        ],
        "name": "泌尿生殖系滴虫病",
        "desc": [
            "泌尿生殖系滴虫病是由阴道鞭毛滴虫引起的泌尿生殖系统的原虫感染，也是一种常见的女性生殖器疾病。男性常因性交或使用污染的内裤、物品和用具等而受到感染，主要感染部位为尿道和前列腺。肾滴虫病是由人阴道毛滴虫所引起的肾盂肾炎，可通过性交传染，也可由尿道上行或经血行感染引起肾脏感染，或通过内裤，游泳、洗浴、便具等途径间接传染，滴虫性膀胱炎是由人阴道毛滴虫所引起的膀胱感染性疾病。滴虫多寄生于妇女阴道后穹隆部或尿道旁腺内，在女性尿道、膀胱、肾脏、前庭大腺内皆可找到;在男性则多寄生于膀胱、尿道和前列腺内，在肾脏、精囊及包皮囊内皆可感染。本病主要通过性接触传染，是一种性传播疾病。患有阴道滴虫病的妇女，配偶中有3%以上亦同时患滴虫病，但多数无明显症状，因此有学者认为滴虫本身并不致病，而与继发细菌感染有关。泌尿生殖系滴虫病可通过实验室检查和膀胱镜检查。泌尿生殖系滴虫病可采用甲硝唑，硝马唑或者用苯扎氯铵或硝酸银溶液冲洗尿道或膀胱。中医中药治疗可采用中药白头翁汤及黄连解毒汤加蛇床子治疗，水煎服，剩药渣再煎后外洗，效果可靠。  "
        ],
        "attributes": [
            "医保疾病： 否 ",
            "患病比例：0.01%",
            "易感人群：无特殊人群  ",
            "传染方式：性传播、接触传播",
            "并发症：胎盘早剥尿道狭窄",
            "就诊科室：外科  泌尿外科",
            "治疗方式：药物治疗 支持性治疗",
            "治疗周期：1-3个月",
            "治愈率：80% ",
            "治疗费用：根据不同医院，收费标准不一致，市三甲医院约（3000——8000元）",
            "注意休息，适当运动。"
        ]
    },
    "cause_info": "(一)发病原因滴虫多寄生于妇女阴道后穹隆部或尿道旁腺内，在男性则多寄生于膀胱，尿道和前列腺内，本病主要通过性接触传染，是一种性传播疾病，患有阴道滴虫病的妇女，配偶中有3%以上亦同时患滴虫病，但多数无明显症状，因此有学者认为滴虫本身并不致病，而与继发细菌感染有关。(二)发病机制毛滴虫对环境的适应能力较强，在35～37℃，pH 5～6时繁殖率最快，正常女性阴道内pH维持在3.8～4.0，故可抑制毛滴虫的繁殖，而在妊娠期及月经前后，阴道内pH增高，同时机体抵抗力下降，容易发生感染，滴虫携带者是本症惟一的传染源。1.直接传染通过性生活男女相互传染，在性关系混乱者及妓女中发病率高，且常与其他性传播疾病如淋病，非淋菌性宫颈炎(支原体，衣原体感染)，尖锐湿疣，细菌性阴道病等同时存在。2.间接传染可通过带滴虫者传染了的内裤，游泳衣，浴巾，卫生巾，厕所，马桶圈，浴盆以及诊查床或未消毒彻底的诊疗器械等传播。(一)发病原因滴虫多寄生于妇女阴道后穹隆部或尿道旁腺内，在男性则多寄生于膀胱，尿道和前列腺内，本病主要通过性接触传染，是一种性传播疾病，患有阴道滴虫病的妇女，配偶中有3%以上亦同时患滴虫病，但多数无明显症状，因此有学者认为滴虫本身并不致病，而与继发细菌感染有关。(二)发病机制毛滴虫对环境的适应能力较强，在35～37℃，pH 5～6时繁殖率最快，正常女性阴道内pH维持在3.8～4.0，故可抑制毛滴虫的繁殖，而在妊娠期及月经前后，阴道内pH增高，同时机体抵抗力下降，容易发生感染，滴虫携带者是本症惟一的传染源。1.直接传染通过性生活男女相互传染，在性关系混乱者及妓女中发病率高，且常与其他性传播疾病如淋病，非淋菌性宫颈炎(支原体，衣原体感染)，尖锐湿疣，细菌性阴道病等同时存在。2.间接传染可通过带滴虫者传染了的内裤，游泳衣，浴巾，卫生巾，厕所，马桶圈，浴盆以及诊查床或未消毒彻底的诊疗器械等传播。",
    "prevent_info": "积极治疗患者及带虫者，对女工和集体生活的女学生定期普查，改善工厂、学校公共卫生设施，加强卫生宣教，注意个人卫生和经期卫生。女用避孕套亦有良好的预防作用。如果夫妻双方有一方感染者(特别是男方感染后无任何症状)，两方均需要进行抗滴虫治疗，避免治愈以后被交叉感染。",
    "symptom_info": [
        [
            "尿痛",
            "尿急",
            "胀痛",
            "尿频",
            "周身不适",
            "畏寒",
            "水肿",
            "排尿不畅",
            "尿道刺痒",
            "血尿",
            "我要提问"
        ],
        [
            "病人多为已婚中年人，常见于女性，有不洁性交史，或配偶有滴虫感染史。1.尿道炎男性病人可出现尿道灼痒，尿频，白色分泌和血尿等，女性病人则出现尿频，尿痛，排尿不畅，阴道分泌物增多，呈浆液性或脓性，可伴异味，耻骨上区疼痛和尿道口水肿等。2.前列腺精囊炎主要表现为前列腺分泌增多，尿终末疼痛，直肠下坠感，会阴部胀痛，直肠指检示前列腺软而大，精囊压痛明显。3.膀胱炎由上行感染引起，可出现尿频，尿急，尿痛及脓血尿。4.外生殖器炎可出现包皮，龟头溃疡，有灼痛感，活组织涂片可找到滴虫。5.畏寒，发热，肾区持续性胀痛，周身不适和胃肠道反应。"
        ]
    ],
    "inspect_info": [
        "阴道毛滴虫检查",
        "膀胱镜",
        "涂片",
        "尿常规",
        "尿沉渣",
        "尿中寄生虫检查"
    ],
    "treat_info": {
        "就诊科室": "外科  泌尿外科",
        "治疗方式": "药物治疗 支持性治疗",
        "治疗周期": "1-3个月",
        "治愈率": "80%",
        "治疗费用": "根据不同医院，收费标准不一致，市三甲医院约（3000——8000元）"
    },
    "food_info": {
        "good": [
            "鸡血",
            "栗子（鲜）",
            "葵花子仁",
            "绿豆"
        ],
        "bad": [
            "干腌菜",
            "白酒",
            "鸡蛋黄",
            "田螺"
        ],
        "recommand": [
            "油菜叶拌豆丝",
            "粉丝拌油菜",
            "香菇烧油菜",
            "芹菜粥",
            "栗子炒芹菜",
            "芹菜炒蛋",
            "芹菜牛肉",
            "牛奶菠菜粥"
        ]
    },
    "drug_info": []
}