{
    "url": "http://jib.xywy.com/il_sii/gaishu/694.htm",
    "basic_info": {
        "category": [
            "疾病百科",
            "急诊科",
            "银杏中毒"
        ],
        "name": "银杏中毒",
        "desc": [
            "白果又名银杏，味带香甜，可以煮或炒食，有祛痰，止咳、润肺、定喘等功效，但大量进食后可引起中毒。白果内含有氢氰酸毒素，毒性很强，遇热后毒性减小，故生食更易中毒。一般中毒剂量为10-50颗，中毒症状发生在进食白果后1-12小时。为预防白果中毒，不宜多吃更不宜生吃白果，本病多见于儿童。  "
        ],
        "attributes": [
            "医保疾病： 否 ",
            "患病比例：0.0001%",
            "易感人群：多见于儿童  ",
            "传染方式：无传染性",
            "并发症：抽搐与惊厥",
            "就诊科室：急诊科  ",
            "治疗方式：药物治疗 支持性治疗",
            "治疗周期：21--30天",
            "治愈率：50% ",
            "治疗费用：根据不同医院，收费标准不一致，市三甲医院约（2000-10000元）",
            "食用银杏时切忌食量过多，要少吃，婴儿勿食，食用时要除去肉中绿色的胚。如发现中毒症状，要及时到医院就诊。"
        ]
    },
    "cause_info": "本病系因大量生食或食未经熟透的白果，而白果内含有氢氰酸毒素所致。采集时与种皮接触，因长时间接触而在皮肤残留毒性而中毒。本病系因大量生食或食未经熟透的白果，而白果内含有氢氰酸毒素所致。采集时与种皮接触，因长时间接触而在皮肤残留毒性而中毒。",
    "prevent_info": "1、因银杏的毒性易溶于水且加热可减弱，所以使用前可用清水浸泡1小时以上，再加热煮熟。2、食用银杏时切忌食量过多，要少吃，婴儿勿食，食用时要除去肉中绿色的胚。3、采集时银杏时避免与种皮接触。",
    "symptom_info": [
        [
            "恶心",
            "腹痛",
            "烦躁不安",
            "腹泻",
            "四肢无力",
            "食欲不振",
            "呼吸困难",
            "惊厥",
            "抽搐",
            "瘫痪",
            "我要提问"
        ],
        [
            "1、有恶心，呕吐，腹痛，腹泻，食欲不振等消化道症状。2、可出现烦躁不安，恐惧，惊厥，肢体强直，抽搐，四肢无力，瘫痪，呼吸困难等症状。"
        ]
    ],
    "inspect_info": [
        "心电图",
        "肾功能检查"
    ],
    "treat_info": {
        "就诊科室": "急诊科  ",
        "治疗方式": "药物治疗 支持性治疗",
        "治疗周期": "21--30天",
        "治愈率": "50%",
        "治疗费用": "根据不同医院，收费标准不一致，市三甲医院约（2000-10000元）"
    },
    "food_info": {
        "good": [],
        "bad": [],
        "recommand": []
    },
    "drug_info": []
}