{
    "url": "http://jib.xywy.com/il_sii/gaishu/7930.htm",
    "basic_info": {
        "category": [
            "疾病百科",
            "内科",
            "消化内科",
            "星形病毒胃肠炎"
        ],
        "name": "星形病毒胃肠炎",
        "desc": [
            "星形病毒胃肠炎是由星形病毒感染所引起的，7岁以下儿童多见，常爆发流行。起病急，临床主要症状以恶心、呕吐，腹痛，腹泻，以水样便为主。  "
        ],
        "attributes": [
            "医保疾病： 否 ",
            "患病比例：发病率约为0.03%--0.06%",
            "易感人群：无特殊人群  ",
            "传染方式：消化道传播 呼吸道传播",
            "并发症：中耳炎支气管炎败血症",
            "就诊科室：内科  消化内科",
            "治疗方式：对症治疗 支持治疗 康复治疗中医中药",
            "治疗周期：2-6周",
            "治愈率：80-90% ",
            "治疗费用：根据不同医院，收费标准不一致，市三甲医院约（3000——8000元）",
            "星形病毒胃肠炎是由星形病毒感染所引起的，7岁以下儿童多见，常爆发流行。起病急，临床主要症状以恶心、呕吐，腹痛，腹泻，以水样便为主。"
        ]
    },
    "cause_info": "(一)发病原因星形病毒(astrovirus)是由Madeley和Cosgrove于1975年首先描述并命名的，病毒颗粒大小不一，平均直径28nm±0.5nm，因病毒表面有5～6个星芒状突起而得此名，有5个抗原型，可在人胚肾细胞中生长。(二)发病机制与肠腺病毒胃肠炎相同。(一)发病原因星形病毒(astrovirus)是由Madeley和Cosgrove于1975年首先描述并命名的，病毒颗粒大小不一，平均直径28nm±0.5nm，因病毒表面有5～6个星芒状突起而得此名，有5个抗原型，可在人胚肾细胞中生长。(二)发病机制与肠腺病毒胃肠炎相同。",
    "prevent_info": "可分为社会性的和个人性的两方面。社会性的预防措施主要由公共卫生部门采取，主要的有：做好公众的健康教育，提高公众的防病意识和能力;做好食品和饮水工作，加强病人、密切接触者及其直接接触环境的管理等工作，积极切断疾病的传染途径。",
    "symptom_info": [
        [
            "腹泻",
            "恶心与呕吐",
            "水样便",
            "腹痛",
            "排便感"
        ],
        [
            "(一)普通轮状病毒胃肠炎 潜伏期1～3天。病情差别较大，6-24月龄小儿症状重，而较大儿童或成年人多为轻型或亚临床感染。起病急，多先吐后泻，伴轻、中度发热。腹泻每日十到数十次不等，大便多为水样，或呈黄绿色稀便，常伴轻或中度脱水及代谢性中毒。部分病例在出现消化道症状前常有上呼吸道感染症状。本病为自限性疾病，病程约1周左右。但少数患儿短期内仍有双糖尤其是乳糖吸收不良，腹泻可持续数周，个别可长达数月。(二)成人腹泻轮状病毒胃肠炎 潜伏期2-3天，起病急，多无发热或仅有低热，以腹泻、腹痛、腹胀为主要症状。腹泻每日3-10次不等，为黄水样或米汤样便，无脓血。部分病例伴恶心、呕吐等症状。病程3-6天，偶可长达10天以上。少数患者可并发肠套叠、直肠出血，溶血尿毒综合征、脑炎及Reye综合征等。"
        ]
    ],
    "inspect_info": [
        "便常规",
        "粪细菌培养",
        "血清免疫球蛋白测定",
        "血清免疫球蛋白M（IgM）",
        "碳源利用试验",
        "酶联免疫吸附试验",
        "血常规",
        "尿常规"
    ],
    "treat_info": {
        "就诊科室": "内科  消化内科",
        "治疗方式": "对症治疗 支持治疗 康复治疗中医中药",
        "治疗周期": "2-6周",
        "治愈率": "80-90%",
        "治疗费用": "根据不同医院，收费标准不一致，市三甲医院约（3000——8000元）"
    },
    "food_info": {
        "good": [],
        "bad": [],
        "recommand": []
    },
    "common_drug": [
        "盐酸左氧氟沙星胶囊",
        "依托红霉素片"
    ],
    "drug_detail": [
        "联邦左福康盐酸左氧氟沙星胶(盐酸左氧氟沙星胶囊)",
        "广东华南依托红霉素片(依托红霉素片)",
        "桂林三金复方红根草片(复方红根草片)",
        "佳乐弗乳酸左氧氟沙星片(乳酸左氧氟沙星片)",
        "沙溪金菊五花茶颗粒(金菊五花茶颗粒)",
        "朗瑞(司帕沙星分散片)",
        "安徽新世纪盐酸左氧氟沙星胶(盐酸左氧氟沙星胶囊)",
        "云鹏呋喃唑酮片(呋喃唑酮片)",
        "巴沙(司帕沙星片)",
        "焱雪雪胆素胶囊(雪胆素胶囊)",
        "中一清泻丸(清泻丸)",
        "哈高科白天鹅乳酸菌素片(乳酸菌素片)",
        "广州一品红复方黄连素片(复方黄连素片)",
        "谷参复方谷氨酰胺肠溶胶囊(复方谷氨酰胺肠溶胶囊)",
        "美常安(枯草杆菌二联活菌肠溶胶囊)",
        "百普力(肠内营养混悬液(SP))",
        "可乐必妥(左氧氟沙星片)",
        "贵州家诚解毒止泻胶囊(解毒止泻胶囊)",
        "四川大冢盐酸左氧氟沙星胶囊(盐酸左氧氟沙星胶囊)",
        "万年青苦木注射液(苦木注射液)",
        "惠州九惠炎宁颗粒(炎宁颗粒)",
        "浙江得恩德氧氟沙星片(氧氟沙星片)",
        "吉林跨海生化止痢宁片(止痢宁片)"
    ]
}